Metadata-Version: 1.0
Name: weibobash
Version: 0.0.1
Summary: 新浪微博命令行工具
Home-page: http://zhuzhezhe.github.io
Author: zhuzhezhe
Author-email: zhuzhezhe95@163.com
License: MIT
Keywords: python weibobash dictionary terminal
Platform: UNKNOWN
